transformers_onnx/__init__.py
transformers_onnx/onnx_model.py
transformers_onnx-0.0.2.dist-info/LICENSE
transformers_onnx-0.0.2.dist-info/METADATA
transformers_onnx-0.0.2.dist-info/WHEEL
transformers_onnx-0.0.2.dist-info/top_level.txt
transformers_onnx-0.0.2.dist-info/RECORD
