Metadata-Version: 2.1
Name: transformers-onnx
Version: 0.0.2
Summary: onnx model for transformers pipeline
Home-page: https://github.com/nlpconnect/transformer_onnx
Author: NLP Connect
Author-email: ankur310794@gmail.com
License: UNKNOWN
Platform: UNKNOWN
Classifier: Programming Language :: Python :: 3
Classifier: License :: OSI Approved :: Apache Software License
Classifier: Operating System :: OS Independent
License-File: LICENSE
Requires-Dist: transformers[onnx]
